{
  "date": "2026-04-24",
  "date_id": "20260424",
  "last_updated": "2026-04-24 19:16:30",
  "source": "20260424.csv",
  "total_picks": 15,
  "stats": {
    "total_stocks": 2796,
    "filtered_stocks": 62,
    "final_picks": 15
  },
  "picks": [
    {
      "code": "0328",
      "name": "3REN",
      "price": 0.39,
      "volume": 106965,
      "b_percent": 63.0,
      "rsi": 50,
      "macd": 0.009,
      "sector_code": "405",
      "sector_name": "Property",
      "total_score": 98,
      "vol_ratio": 0.27,
      "daily_change": 0.04,
      "reasons": "B% 63.0%; RSI中性; MACD金叉; 大涨4.0%",
      "risk": "低",
      "risk_label": "🔥強烈買入"
    },
    {
      "code": "020823",
      "name": "GREATEC-C23",
      "price": 0.31,
      "volume": 60221,
      "b_percent": 55.0,
      "rsi": 50,
      "macd": 0.024,
      "sector_code": "305",
      "sector_name": "Technology",
      "total_score": 98,
      "vol_ratio": 0.03,
      "daily_change": 0.145,
      "reasons": "B% 55.0%; RSI中性; MACD金叉; 大涨14.5%",
      "risk": "低",
      "risk_label": "🔥強烈買入"
    },
    {
      "code": "5148",
      "name": "UEMS",
      "price": 0.55,
      "volume": 327963,
      "b_percent": 54.0,
      "rsi": 50,
      "macd": 0.001,
      "sector_code": "120",
      "sector_name": "Industrial & Consumer Products",
      "total_score": 96,
      "vol_ratio": 0.05,
      "daily_change": 0.03,
      "reasons": "B% 54.0%; RSI中性; MACD金叉; 涨3.0%",
      "risk": "低",
      "risk_label": "🔥強烈買入"
    },
    {
      "code": "0129",
      "name": "SRIDGE",
      "price": 0.37,
      "volume": 75655,
      "b_percent": 65.0,
      "rsi": 50,
      "macd": 0.004,
      "sector_code": "463",
      "sector_name": "Property",
      "total_score": 96,
      "vol_ratio": 0.01,
      "daily_change": 0.015,
      "reasons": "B% 65.0%; RSI中性; MACD金叉; 涨1.5%",
      "risk": "低",
      "risk_label": "🔥強烈買入"
    },
    {
      "code": "0167",
      "name": "MCLEAN",
      "price": 0.62,
      "volume": 82076,
      "b_percent": 53.0,
      "rsi": 50,
      "macd": 0.017,
      "sector_code": "402",
      "sector_name": "Property",
      "total_score": 96,
      "vol_ratio": 0.03,
      "daily_change": 0.025,
      "reasons": "B% 53.0%; RSI中性; MACD金叉; 涨2.5%",
      "risk": "低",
      "risk_label": "🔥強烈買入"
    },
    {
      "code": "0399",
      "name": "AMS",
      "price": 0.345,
      "volume": 397529,
      "b_percent": 72.0,
      "rsi": 50,
      "macd": 0.0,
      "sector_code": "402",
      "sector_name": "Property",
      "total_score": 95,
      "vol_ratio": 1.0,
      "daily_change": 0.04,
      "reasons": "B% 72.0%; RSI中性; 大涨4.0%",
      "risk": "低",
      "risk_label": "🔥強烈買入"
    },
    {
      "code": "6971",
      "name": "KOBAY",
      "price": 1.94,
      "volume": 79303,
      "b_percent": 67.0,
      "rsi": 50,
      "macd": 0.049,
      "sector_code": "102",
      "sector_name": "Industrial & Consumer Products",
      "total_score": 95,
      "vol_ratio": 0.14,
      "daily_change": 0.21,
      "reasons": "B% 67.0%; RSI中性; MACD金叉; 大涨21.0%",
      "risk": "低",
      "risk_label": "🔥強烈買入"
    },
    {
      "code": "7233",
      "name": "DUFU",
      "price": 1.76,
      "volume": 127978,
      "b_percent": 54.0,
      "rsi": 50,
      "macd": 0.05,
      "sector_code": "102",
      "sector_name": "Industrial & Consumer Products",
      "total_score": 95,
      "vol_ratio": 0.02,
      "daily_change": 0.05,
      "reasons": "B% 54.0%; RSI中性; MACD金叉; 大涨5.0%",
      "risk": "低",
      "risk_label": "🔥強烈買入"
    },
    {
      "code": "5351",
      "name": "EMPIRE",
      "price": 0.99,
      "volume": 132114,
      "b_percent": 50.0,
      "rsi": 50,
      "macd": 0.0,
      "sector_code": "101",
      "sector_name": "Industrial & Consumer Products",
      "total_score": 93,
      "vol_ratio": 1.0,
      "daily_change": 0.015,
      "reasons": "B% 50.0%; RSI中性; 涨1.5%",
      "risk": "低",
      "risk_label": "🔥強烈買入"
    },
    {
      "code": "5243",
      "name": "VELESTO",
      "price": 0.32,
      "volume": 262287,
      "b_percent": 50.0,
      "rsi": 50,
      "macd": 0.002,
      "sector_code": "161",
      "sector_name": "Industrial & Consumer Products",
      "total_score": 93,
      "vol_ratio": 0.01,
      "daily_change": 0.0,
      "reasons": "B% 50.0%; RSI中性; MACD金叉",
      "risk": "低",
      "risk_label": "🔥強烈買入"
    },
    {
      "code": "0262",
      "name": "SUNVIEW",
      "price": 0.365,
      "volume": 56623,
      "b_percent": 60.0,
      "rsi": 50,
      "macd": 0.001,
      "sector_code": "461",
      "sector_name": "Property",
      "total_score": 93,
      "vol_ratio": 0.01,
      "daily_change": 0.005,
      "reasons": "B% 60.0%; RSI中性; MACD金叉",
      "risk": "低",
      "risk_label": "🔥強烈買入"
    },
    {
      "code": "8664",
      "name": "SPSETIA",
      "price": 0.96,
      "volume": 112404,
      "b_percent": 60.0,
      "rsi": 50,
      "macd": 0.01,
      "sector_code": "120",
      "sector_name": "Industrial & Consumer Products",
      "total_score": 93,
      "vol_ratio": 0.01,
      "daily_change": -0.01,
      "reasons": "B% 60.0%; RSI中性; MACD金叉",
      "risk": "低",
      "risk_label": "🔥強烈買入"
    },
    {
      "code": "0270",
      "name": "NATGATE",
      "price": 0.785,
      "volume": 77962,
      "b_percent": 50.0,
      "rsi": 50,
      "macd": 0.013,
      "sector_code": "102",
      "sector_name": "Industrial & Consumer Products",
      "total_score": 93,
      "vol_ratio": 0.01,
      "daily_change": 0.0,
      "reasons": "B% 50.0%; RSI中性; MACD金叉",
      "risk": "低",
      "risk_label": "🔥強烈買入"
    },
    {
      "code": "0024",
      "name": "JAG",
      "price": 0.36,
      "volume": 67226,
      "b_percent": 73.0,
      "rsi": 50,
      "macd": 0.005,
      "sector_code": "402",
      "sector_name": "Property",
      "total_score": 93,
      "vol_ratio": 0.01,
      "daily_change": 0.005,
      "reasons": "B% 73.0%; RSI中性; MACD金叉",
      "risk": "低",
      "risk_label": "🔥強烈買入"
    },
    {
      "code": "0138",
      "name": "ZETRIX",
      "price": 0.86,
      "volume": 594660,
      "b_percent": 50.0,
      "rsi": 50,
      "macd": 0.024,
      "sector_code": "105",
      "sector_name": "Industrial & Consumer Products",
      "total_score": 93,
      "vol_ratio": 0.01,
      "daily_change": -0.005,
      "reasons": "B% 50.0%; RSI中性; MACD金叉",
      "risk": "低",
      "risk_label": "🔥強烈買入"
    }
  ]
}